{
    "asset": {
        "format": "jpg",
        "id": "592a385840350129d64f71ff53be4075",
        "name": "inv3.jpg",
        "path": "file:/Users/rajeshkumaran/Documents/Projects/OCREngine/TrainYourOwnYOLO/Data/Source_Images/Training_Images/inv3.jpg",
        "size": {
            "width": 750,
            "height": 1000
        },
        "state": 2,
        "type": 1
    },
    "regions": [
        {
            "id": "_X2iLAONF",
            "type": "RECTANGLE",
            "tags": [
                "name"
            ],
            "boundingBox": {
                "height": 98.90220905172413,
                "width": 214.08045977011494,
                "left": 123.56883081896551,
                "top": 511.8366109913793
            },
            "points": [
                {
                    "x": 123.56883081896551,
                    "y": 511.8366109913793
                },
                {
                    "x": 337.64929058908046,
                    "y": 511.8366109913793
                },
                {
                    "x": 337.64929058908046,
                    "y": 610.7388200431034
                },
                {
                    "x": 123.56883081896551,
                    "y": 610.7388200431034
                }
            ]
        },
        {
            "id": "8cnGiv4rO",
            "type": "RECTANGLE",
            "tags": [
                "price"
            ],
            "boundingBox": {
                "height": 106.27132722701148,
                "width": 98.492501795977,
                "left": 565.6036727729885,
                "top": 509.1707076149425
            },
            "points": [
                {
                    "x": 565.6036727729885,
                    "y": 509.1707076149425
                },
                {
                    "x": 664.0961745689655,
                    "y": 509.1707076149425
                },
                {
                    "x": 664.0961745689655,
                    "y": 615.442034841954
                },
                {
                    "x": 565.6036727729885,
                    "y": 615.442034841954
                }
            ]
        }
    ],
    "version": "2.1.0"
}