{
    "asset": {
        "format": "jpg",
        "id": "ece516945d862ace2b370357469a0ab4",
        "name": "Halgekar%25202.jpg",
        "path": "file:/Users/srinisa/Documents/Personal%20Projects/TrainYourOwnYOLO/Data/Source_Images/Test_Images/Halgekar%25202.jpg",
        "size": {
            "width": 2805,
            "height": 4009
        },
        "state": 2,
        "type": 1
    },
    "regions": [
        {
            "id": "B61pB7JbJ",
            "type": "RECTANGLE",
            "tags": [
                "dealer"
            ],
            "boundingBox": {
                "height": 143.82933846734372,
                "width": 733.4158531200942,
                "left": 1111.6312426412874,
                "top": 255.23819978046106
            },
            "points": [
                {
                    "x": 1111.6312426412874,
                    "y": 255.23819978046106
                },
                {
                    "x": 1845.0470957613816,
                    "y": 255.23819978046106
                },
                {
                    "x": 1845.0470957613816,
                    "y": 399.06753824780475
                },
                {
                    "x": 1111.6312426412874,
                    "y": 399.06753824780475
                }
            ]
        },
        {
            "id": "neSoF6QLm",
            "type": "RECTANGLE",
            "tags": [
                "description"
            ],
            "boundingBox": {
                "height": 308.5102351468167,
                "width": 914.5078860871272,
                "left": 319.2331914737049,
                "top": 1370.8911095293633
            },
            "points": [
                {
                    "x": 319.2331914737049,
                    "y": 1370.8911095293633
                },
                {
                    "x": 1233.741077560832,
                    "y": 1370.8911095293633
                },
                {
                    "x": 1233.741077560832,
                    "y": 1679.40134467618
                },
                {
                    "x": 319.2331914737049,
                    "y": 1679.40134467618
                }
            ]
        },
        {
            "id": "cJ1d5ItOh",
            "type": "RECTANGLE",
            "tags": [
                "amount"
            ],
            "boundingBox": {
                "height": 201.0207104143798,
                "width": 243.6692381279435,
                "left": 2433.0973741660127,
                "top": 1481.8358388789793
            },
            "points": [
                {
                    "x": 2433.0973741660127,
                    "y": 1481.8358388789793
                },
                {
                    "x": 2676.7666122939563,
                    "y": 1481.8358388789793
                },
                {
                    "x": 2676.7666122939563,
                    "y": 1682.856549293359
                },
                {
                    "x": 2433.0973741660127,
                    "y": 1682.856549293359
                }
            ]
        }
    ],
    "version": "2.1.0"
}